{
    "formTemplate": "normal",
    "head": {
        "type": "element",
        "elementType": "Header",
        "elementProps": {
            "canBack": true,
            "titleElement": {
                "type": "element",
                "elementType": "FormTitle",
                "elementProps": {
                    "containerStyle": {
                        "alignItems": "center",
                        "justifyContent": "center"
                    }
                }
            }
        }
    },
    "items": [
        "DocumentNumber",
        "Creator",
        "DocumentDate1",
        "DocumentDate2",
        "SalesDocumentTypesID",
        "SaleAreaID",
        "PlantID",
        "MaterialID",
        "StorageLocationID"
    ],
    "foot": {
        "type": "element",
        "elementType": "SegementToolbarButton",
        "elementProps": {
            "buttons": [
                {
                    "key": "OK",
                    "caption": "确定"
                },
                "Cancel"
            ]
        }
    }
}